{"uf": "DF", "cep": "71200010", "qsa": [{"pais": null, "nome_socio": "SEBASTIAO DE CARVALHO NETO", "codigo_pais": null, "faixa_etaria": "Entre 71 a 80 anos", "cnpj_cpf_do_socio": "***922351**", "qualificacao_socio": "Diretor", "codigo_faixa_etaria": 8, "data_entrada_sociedade": "1999-08-20", "identificador_de_socio": 2, "cpf_representante_legal": "***000000**", "nome_representante_legal": "", "codigo_qualificacao_socio": 10, "qualificacao_representante_legal": "Diretor", "codigo_qualificacao_representante_legal": 0}, {"pais": null, "nome_socio": "ALUIZIO CRISPIM DE CARVALHO", "codigo_pais": null, "faixa_etaria": "Entre 61 a 70 anos", "cnpj_cpf_do_socio": "***537821**", "qualificacao_socio": "Diretor", "codigo_faixa_etaria": 7, "data_entrada_sociedade": "1999-08-20", "identificador_de_socio": 2, "cpf_representante_legal": "***000000**", "nome_representante_legal": "", "codigo_qualificacao_socio": 10, "qualificacao_representante_legal": "Diretor", "codigo_qualificacao_representante_legal": 0}, {"pais": null, "nome_socio": "HILTON CRISPIM DE CARVALHO", "codigo_pais": null, "faixa_etaria": "Entre 61 a 70 anos", "cnpj_cpf_do_socio": "***538121**", "qualificacao_socio": "Diretor", "codigo_faixa_etaria": 7, "data_entrada_sociedade": "1999-08-20", "identificador_de_socio": 2, "cpf_representante_legal": "***000000**", "nome_representante_legal": "", "codigo_qualificacao_socio": 10, "qualificacao_representante_legal": "Diretor", "codigo_qualificacao_representante_legal": 0}, {"pais": null, "nome_socio": "FABIANA TRIGUEIRO DE CARVALHO", "codigo_pais": null, "faixa_etaria": "Entre 41 a 50 anos", "cnpj_cpf_do_socio": "***003731**", "qualificacao_socio": "Diretor", "codigo_faixa_etaria": 5, "data_entrada_sociedade": "2022-06-09", "identificador_de_socio": 2, "cpf_representante_legal": "***000000**", "nome_representante_legal": "", "codigo_qualificacao_socio": 10, "qualificacao_representante_legal": "Diretor", "codigo_qualificacao_representante_legal": 0}, {"pais": null, "nome_socio": "VINICIUS FARIAS DE CARVALHO", "codigo_pais": null, "faixa_etaria": "Entre 21 a 30 anos", "cnpj_cpf_do_socio": "***452321**", "qualificacao_socio": "Diretor", "codigo_faixa_etaria": 3, "data_entrada_sociedade": "2022-06-09", "identificador_de_socio": 2, "cpf_representante_legal": "***000000**", "nome_representante_legal": "", "codigo_qualificacao_socio": 10, "qualificacao_representante_legal": "Diretor", "codigo_qualificacao_representante_legal": 0}, {"pais": null, "nome_socio": "LUIZ GUILHERME MIRANDA CARVALHO", "codigo_pais": null, "faixa_etaria": "Entre 31 a 40 anos", "cnpj_cpf_do_socio": "***646138**", "qualificacao_socio": "Diretor", "codigo_faixa_etaria": 4, "data_entrada_sociedade": "2022-06-09", "identificador_de_socio": 2, "cpf_representante_legal": "***000000**", "nome_representante_legal": "", "codigo_qualificacao_socio": 10, "qualificacao_representante_legal": "Diretor", "codigo_qualificacao_representante_legal": 0}, {"pais": null, "nome_socio": "CECILIA LELIS DE CARVALHO", "codigo_pais": null, "faixa_etaria": "Entre 21 a 30 anos", "cnpj_cpf_do_socio": "***142781**", "qualificacao_socio": "Diretor", "codigo_faixa_etaria": 3, "data_entrada_sociedade": "2022-06-09", "identificador_de_socio": 2, "cpf_representante_legal": "***000000**", "nome_representante_legal": "", "codigo_qualificacao_socio": 10, "qualificacao_representante_legal": "Diretor", "codigo_qualificacao_representante_legal": 0}, {"pais": null, "nome_socio": "LUIZ FELLIPE GONCALVES DE CARVALHO", "codigo_pais": null, "faixa_etaria": "Entre 31 a 40 anos", "cnpj_cpf_do_socio": "***602101**", "qualificacao_socio": "Diretor", "codigo_faixa_etaria": 4, "data_entrada_sociedade": "2022-06-09", "identificador_de_socio": 2, "cpf_representante_legal": "***000000**", "nome_representante_legal": "", "codigo_qualificacao_socio": 10, "qualificacao_representante_legal": "Diretor", "codigo_qualificacao_representante_legal": 0}], "cnpj": "00000802000100", "pais": null, "email": null, "porte": "DEMAIS", "bairro": "SETOR DE INDUSTRIA", "numero": "01", "ddd_fax": "6121061812", "municipio": "BRASILIA", "logradouro": "SIA TRECHO", "cnae_fiscal": 4530702, "codigo_pais": null, "complemento": "LOTE 1711", "codigo_porte": 5, "razao_social": "HC PNEUS S/A", "nome_fantasia": "HC PNEUS", "capital_social": 153835620, "ddd_telefone_1": "6121061800", "ddd_telefone_2": "6121061812", "opcao_pelo_mei": null, "descricao_porte": "", "codigo_municipio": 9701, "cnaes_secundarios": [{"codigo": 4530705, "descricao": "Comércio a varejo de pneumáticos e câmaras-de-ar"}, {"codigo": 4530703, "descricao": "Comércio a varejo de peças e acessórios novos para veículos automotores"}, {"codigo": 4520004, "descricao": "Serviços de alinhamento e balanceamento de veículos automotores"}, {"codigo": 4520001, "descricao": "Serviços de manutenção e reparação mecânica de veículos automotores"}], "natureza_juridica": "Sociedade Anônima Fechada", "situacao_especial": "", "opcao_pelo_simples": null, "situacao_cadastral": 2, "data_opcao_pelo_mei": null, "data_exclusao_do_mei": null, "cnae_fiscal_descricao": "Comércio por atacado de pneumáticos e câmaras-de-ar", "codigo_municipio_ibge": 5300108, "data_inicio_atividade": "1966-08-24", "data_situacao_especial": null, "data_opcao_pelo_simples": null, "data_situacao_cadastral": "2005-11-03", "nome_cidade_no_exterior": "", "codigo_natureza_juridica": 2054, "data_exclusao_do_simples": null, "motivo_situacao_cadastral": 0, "ente_federativo_responsavel": "", "identificador_matriz_filial": 1, "qualificacao_do_responsavel": 10, "descricao_situacao_cadastral": "ATIVA", "descricao_tipo_de_logradouro": "SETOR", "descricao_motivo_situacao_cadastral": "SEM MOTIVO", "descricao_identificador_matriz_filial": "MATRIZ"}