{"uf": "DF", "cep": "71936250", "qsa": [{"pais": null, "nome_socio": "DENISE BARREL COTA", "codigo_pais": null, "faixa_etaria": "Entre 61 a 70 anos", "cnpj_cpf_do_socio": "***015626**", "qualificacao_socio": "Titular Pessoa Física Residente ou Domiciliado no Brasil", "codigo_faixa_etaria": 7, "data_entrada_sociedade": "2001-01-08", "identificador_de_socio": 2, "cpf_representante_legal": "***000000**", "nome_representante_legal": "", "codigo_qualificacao_socio": 65, "qualificacao_representante_legal": "Titular Pessoa Física Residente ou Domiciliado no Brasil", "codigo_qualificacao_representante_legal": 0}], "cnpj": "03764895000129", "pais": null, "email": null, "porte": "MICRO EMPRESA", "bairro": "SUL (AGUAS CLARAS)", "numero": "305", "ddd_fax": "", "municipio": "BRASILIA", "logradouro": "DAS ARAUCARIAS LOTE", "cnae_fiscal": 7319002, "codigo_pais": null, "complemento": "LOJA 32 TERREO", "codigo_porte": 1, "razao_social": "TECNO INDUSTRIAL E COMERCIAL EIRELI", "nome_fantasia": "TECNO INDUSTRIAL E COMERCIAL", "capital_social": 99800, "ddd_telefone_1": "6181344341", "ddd_telefone_2": "3195214714", "opcao_pelo_mei": false, "descricao_porte": "", "codigo_municipio": 9701, "cnaes_secundarios": [{"codigo": 4321500, "descricao": "Instalação e manutenção elétrica"}, {"codigo": 4322301, "descricao": "Instalações hidráulicas, sanitárias e de gás"}, {"codigo": 4613300, "descricao": "Representantes comerciais e agentes do comércio de madeira, material de construção e ferragens"}, {"codigo": 4742300, "descricao": "Comércio varejista de material elétrico"}, {"codigo": 4744001, "descricao": "Comércio varejista de ferragens e ferramentas"}], "natureza_juridica": "Empresa Individual de Responsabilidade Limitada (de Natureza Empresária)", "situacao_especial": "", "opcao_pelo_simples": true, "situacao_cadastral": 2, "data_opcao_pelo_mei": null, "data_exclusao_do_mei": null, "cnae_fiscal_descricao": "Promoção de vendas", "codigo_municipio_ibge": 5300108, "data_inicio_atividade": "2000-04-19", "data_situacao_especial": null, "data_opcao_pelo_simples": "2018-01-01", "data_situacao_cadastral": "2005-11-03", "nome_cidade_no_exterior": "", "codigo_natureza_juridica": 2305, "data_exclusao_do_simples": null, "motivo_situacao_cadastral": 0, "ente_federativo_responsavel": "", "identificador_matriz_filial": 1, "qualificacao_do_responsavel": 65, "descricao_situacao_cadastral": "ATIVA", "descricao_tipo_de_logradouro": "AVENIDA", "descricao_motivo_situacao_cadastral": "SEM MOTIVO", "descricao_identificador_matriz_filial": "MATRIZ"}