{"uf": "PR", "cep": "80060100", "qsa": [{"pais": null, "nome_socio": "MARINO GALVAO JUNIOR", "codigo_pais": null, "faixa_etaria": "Entre 41 a 50 anos", "cnpj_cpf_do_socio": "***916259**", "qualificacao_socio": "Diretor", "codigo_faixa_etaria": 5, "data_entrada_sociedade": "2015-05-20", "identificador_de_socio": 2, "cpf_representante_legal": "***000000**", "nome_representante_legal": "", "codigo_qualificacao_socio": 10, "qualificacao_representante_legal": "Diretor", "codigo_qualificacao_representante_legal": 0}], "cnpj": "05503775000101", "pais": null, "email": null, "porte": "DEMAIS", "bairro": "CENTRO", "numero": "273", "ddd_fax": "", "municipio": "CURITIBA", "logradouro": "CONSELHEIRO LAURINDO", "cnae_fiscal": 9493600, "codigo_pais": null, "complemento": "", "codigo_porte": 5, "razao_social": "CURITIBA ARTE-INSTITUTO CURITIBA DE ARTE E CULTURA", "nome_fantasia": "", "capital_social": 0, "ddd_telefone_1": "4132235710", "ddd_telefone_2": "4196661482", "opcao_pelo_mei": null, "descricao_porte": "", "codigo_municipio": 7535, "cnaes_secundarios": [{"codigo": 4789001, "descricao": "Comércio varejista de suvenires, bijuterias e artesanatos"}, {"codigo": 5914600, "descricao": "Atividades de exibição cinematográfica"}, {"codigo": 7220700, "descricao": "Pesquisa e desenvolvimento experimental em ciências sociais e humanas"}, {"codigo": 7490199, "descricao": "Outras atividades profissionais, científicas e técnicas não especificadas anteriormente"}, {"codigo": 8592901, "descricao": "Ensino de dança"}, {"codigo": 8592903, "descricao": "Ensino de música"}, {"codigo": 9001902, "descricao": "Produção musical"}, {"codigo": 9001903, "descricao": "Produção de espetáculos de dança"}, {"codigo": 9001999, "descricao": "Artes cênicas, espetáculos e atividades complementares não especificadas anteriormente"}, {"codigo": 9003500, "descricao": "Gestão de espaços para artes cênicas, espetáculos e outras atividades artísticas"}, {"codigo": 9101500, "descricao": "Atividades de bibliotecas e arquivos"}, {"codigo": 9102301, "descricao": "Atividades de museus e de exploração de lugares e prédios históricos e atrações similares"}], "natureza_juridica": "Associação Privada", "situacao_especial": "", "opcao_pelo_simples": null, "situacao_cadastral": 2, "data_opcao_pelo_mei": null, "data_exclusao_do_mei": null, "cnae_fiscal_descricao": "Atividades de organizações associativas ligadas à cultura e à arte", "codigo_municipio_ibge": 4106902, "data_inicio_atividade": "2003-01-23", "data_situacao_especial": null, "data_opcao_pelo_simples": null, "data_situacao_cadastral": "2003-01-23", "nome_cidade_no_exterior": "", "codigo_natureza_juridica": 3999, "data_exclusao_do_simples": null, "motivo_situacao_cadastral": 0, "ente_federativo_responsavel": "", "identificador_matriz_filial": 1, "qualificacao_do_responsavel": 10, "descricao_situacao_cadastral": "ATIVA", "descricao_tipo_de_logradouro": "RUA", "descricao_motivo_situacao_cadastral": "SEM MOTIVO", "descricao_identificador_matriz_filial": "MATRIZ"}