{"uf": "SC", "cep": "88010000", "qsa": [{"pais": null, "nome_socio": "CAROLINE MACHADO COSTA", "codigo_pais": null, "faixa_etaria": "Entre 31 a 40 anos", "cnpj_cpf_do_socio": "***864489**", "qualificacao_socio": "Sócio-Administrador", "codigo_faixa_etaria": 4, "data_entrada_sociedade": "2011-11-08", "identificador_de_socio": 2, "cpf_representante_legal": "***000000**", "nome_representante_legal": "", "codigo_qualificacao_socio": 49, "qualificacao_representante_legal": "Sócio-Administrador", "codigo_qualificacao_representante_legal": 0}, {"pais": null, "nome_socio": "TAMARA TEIXEIRA ARAGAO OLIVEIRA", "codigo_pais": null, "faixa_etaria": "Entre 31 a 40 anos", "cnpj_cpf_do_socio": "***840119**", "qualificacao_socio": "Sócio-Administrador", "codigo_faixa_etaria": 4, "data_entrada_sociedade": "2012-11-27", "identificador_de_socio": 2, "cpf_representante_legal": "***000000**", "nome_representante_legal": "", "codigo_qualificacao_socio": 49, "qualificacao_representante_legal": "Sócio-Administrador", "codigo_qualificacao_representante_legal": 0}, {"pais": null, "nome_socio": "PAULO JOSE ARAGAO JUNIOR", "codigo_pais": null, "faixa_etaria": "Entre 31 a 40 anos", "cnpj_cpf_do_socio": "***623619**", "qualificacao_socio": "Sócio", "codigo_faixa_etaria": 4, "data_entrada_sociedade": "2012-11-27", "identificador_de_socio": 2, "cpf_representante_legal": "***000000**", "nome_representante_legal": "", "codigo_qualificacao_socio": 22, "qualificacao_representante_legal": "Sócio", "codigo_qualificacao_representante_legal": 0}, {"pais": null, "nome_socio": "GUSTAVO MACHADO COSTA", "codigo_pais": null, "faixa_etaria": "Entre 31 a 40 anos", "cnpj_cpf_do_socio": "***978649**", "qualificacao_socio": "Sócio", "codigo_faixa_etaria": 4, "data_entrada_sociedade": "2012-11-27", "identificador_de_socio": 2, "cpf_representante_legal": "***000000**", "nome_representante_legal": "", "codigo_qualificacao_socio": 22, "qualificacao_representante_legal": "Sócio", "codigo_qualificacao_representante_legal": 0}], "cnpj": "14596598000138", "pais": null, "email": null, "porte": "MICRO EMPRESA", "bairro": "CENTRO", "numero": "649", "ddd_fax": "4832660212", "municipio": "FLORIANOPOLIS", "logradouro": "FELIPE SCHMIDT", "cnae_fiscal": 7112000, "codigo_pais": null, "complemento": "SALA 306 EDIF TORRE DA COLINA", "codigo_porte": 1, "razao_social": "RACA SERVICOS AMBIENTAIS, OFICINAS EDUCATIVAS LTDA", "nome_fantasia": "RACA AMBIENTAL E EDUCACAO", "capital_social": 60000, "ddd_telefone_1": "4832660212", "ddd_telefone_2": "4832660112", "opcao_pelo_mei": false, "descricao_porte": "", "codigo_municipio": 8105, "cnaes_secundarios": [{"codigo": 7020400, "descricao": "Atividades de consultoria em gestão empresarial, exceto consultoria técnica específica"}, {"codigo": 7119701, "descricao": "Serviços de cartografia, topografia e geodésia"}, {"codigo": 7490199, "descricao": "Outras atividades profissionais, científicas e técnicas não especificadas anteriormente"}, {"codigo": 8550302, "descricao": "Atividades de apoio à educação, exceto caixas escolares"}], "natureza_juridica": "Sociedade Empresária Limitada", "situacao_especial": "", "opcao_pelo_simples": true, "situacao_cadastral": 2, "data_opcao_pelo_mei": null, "data_exclusao_do_mei": null, "cnae_fiscal_descricao": "Serviços de engenharia", "codigo_municipio_ibge": 4205407, "data_inicio_atividade": "2011-11-08", "data_situacao_especial": null, "data_opcao_pelo_simples": "2015-01-01", "data_situacao_cadastral": "2011-11-08", "nome_cidade_no_exterior": "", "codigo_natureza_juridica": 2062, "data_exclusao_do_simples": null, "motivo_situacao_cadastral": 0, "ente_federativo_responsavel": "", "identificador_matriz_filial": 1, "qualificacao_do_responsavel": 49, "descricao_situacao_cadastral": "ATIVA", "descricao_tipo_de_logradouro": "RUA", "descricao_motivo_situacao_cadastral": "SEM MOTIVO", "descricao_identificador_matriz_filial": "MATRIZ"}