{"uf": "SP", "cep": "13337300", "qsa": [{"pais": null, "nome_socio": "MARCOS HACKER DE MELO", "codigo_pais": null, "faixa_etaria": "Entre 31 a 40 anos", "cnpj_cpf_do_socio": "***684544**", "qualificacao_socio": "Presidente", "codigo_faixa_etaria": 4, "data_entrada_sociedade": "2018-03-08", "identificador_de_socio": 2, "cpf_representante_legal": "***000000**", "nome_representante_legal": "", "codigo_qualificacao_socio": 16, "qualificacao_representante_legal": "Presidente", "codigo_qualificacao_representante_legal": 0}, {"pais": null, "nome_socio": "JATHIACY SANSONIO TAVARES", "codigo_pais": null, "faixa_etaria": "Entre 41 a 50 anos", "cnpj_cpf_do_socio": "***881014**", "qualificacao_socio": "Diretor", "codigo_faixa_etaria": 5, "data_entrada_sociedade": "2018-06-25", "identificador_de_socio": 2, "cpf_representante_legal": "***000000**", "nome_representante_legal": "", "codigo_qualificacao_socio": 10, "qualificacao_representante_legal": "Diretor", "codigo_qualificacao_representante_legal": 0}, {"pais": null, "nome_socio": "MARIA APARECIDA HACKER DE MELO", "codigo_pais": null, "faixa_etaria": "Entre 51 a 60 anos", "cnpj_cpf_do_socio": "***123424**", "qualificacao_socio": "Administrador", "codigo_faixa_etaria": 6, "data_entrada_sociedade": "2020-10-22", "identificador_de_socio": 2, "cpf_representante_legal": "***000000**", "nome_representante_legal": "", "codigo_qualificacao_socio": 5, "qualificacao_representante_legal": "Administrador", "codigo_qualificacao_representante_legal": 0}], "cnpj": "15652882000732", "pais": null, "email": null, "porte": "DEMAIS", "bairro": "HELVETIA", "numero": "S/N", "ddd_fax": "1938851725", "municipio": "INDAIATUBA", "logradouro": "ENGENHEIRO ERMENIO DE OLIVEIRA PENTEADO (SP-075)", "cnae_fiscal": 4662100, "codigo_pais": null, "complemento": ": MARGINAL NORTE; KM: 598;", "codigo_porte": 5, "razao_social": "VENEZA EQUIPAMENTOS PESADOS S/A", "nome_fantasia": "VENEZA EQUIPAMENTOS", "capital_social": 27080000, "ddd_telefone_1": "1931155100", "ddd_telefone_2": "", "opcao_pelo_mei": null, "descricao_porte": "", "codigo_municipio": 6511, "cnaes_secundarios": [{"codigo": 3314708, "descricao": "Manutenção e reparação de máquinas, equipamentos e aparelhos para transporte e elevação de cargas"}, {"codigo": 3314717, "descricao": "Manutenção e reparação de máquinas e equipamentos de terraplenagem, pavimentação e construção, exceto tratores"}, {"codigo": 4614100, "descricao": "Representantes comerciais e agentes do comércio de máquinas, equipamentos, embarcações e aeronaves"}, {"codigo": 4669999, "descricao": "Comércio atacadista de outras máquinas e equipamentos não especificados anteriormente; partes e peças"}, {"codigo": 6463800, "descricao": "Outras sociedades de participação, exceto holdings"}, {"codigo": 7490104, "descricao": "Atividades de intermediação e agenciamento de serviços e negócios em geral, exceto imobiliários"}, {"codigo": 7732201, "descricao": "Aluguel de máquinas e equipamentos para construção sem operador, exceto andaimes"}, {"codigo": 7739099, "descricao": "Aluguel de outras máquinas e equipamentos comerciais e industriais não especificados anteriormente, sem operador"}, {"codigo": 5211701, "descricao": "Armazéns gerais - emissão de warrant"}], "natureza_juridica": "Sociedade Anônima Fechada", "situacao_especial": "", "opcao_pelo_simples": null, "situacao_cadastral": 2, "data_opcao_pelo_mei": null, "data_exclusao_do_mei": null, "cnae_fiscal_descricao": "Comércio atacadista de máquinas, equipamentos para terraplenagem, mineração e construção; partes e peças", "codigo_municipio_ibge": 3520509, "data_inicio_atividade": "2014-03-26", "data_situacao_especial": null, "data_opcao_pelo_simples": null, "data_situacao_cadastral": "2014-03-26", "nome_cidade_no_exterior": "", "codigo_natureza_juridica": 2054, "data_exclusao_do_simples": null, "motivo_situacao_cadastral": 0, "ente_federativo_responsavel": "", "identificador_matriz_filial": 2, "qualificacao_do_responsavel": 5, "descricao_situacao_cadastral": "ATIVA", "descricao_tipo_de_logradouro": "RODOVIA", "descricao_motivo_situacao_cadastral": "SEM MOTIVO", "descricao_identificador_matriz_filial": "FILIAL"}