{"uf": "RS", "cep": "93010220", "qsa": [{"pais": null, "nome_socio": "MARGIT KOLLING", "codigo_pais": null, "faixa_etaria": "Entre 51 a 60 anos", "cnpj_cpf_do_socio": "***821420**", "qualificacao_socio": "Sócio-Administrador", "codigo_faixa_etaria": 6, "data_entrada_sociedade": "2022-07-14", "identificador_de_socio": 2, "cpf_representante_legal": "***000000**", "nome_representante_legal": "", "codigo_qualificacao_socio": 49, "qualificacao_representante_legal": "Sócio-Administrador", "codigo_qualificacao_representante_legal": 0}], "cnpj": "23344266000157", "pais": null, "email": null, "porte": "MICRO EMPRESA", "bairro": "CENTRO", "numero": "806", "ddd_fax": "", "municipio": "SAO LEOPOLDO", "logradouro": "BENTO GONCALVES", "cnae_fiscal": 8592999, "codigo_pais": null, "complemento": "SALA 303", "codigo_porte": 1, "razao_social": "ARTE&IDEIAS GESTAO E PRODUCAO LTDA", "nome_fantasia": "ARTE&IDEIAS", "capital_social": 10000, "ddd_telefone_1": "5199786155", "ddd_telefone_2": "", "opcao_pelo_mei": false, "descricao_porte": "", "codigo_municipio": 8877, "cnaes_secundarios": [{"codigo": 4761001, "descricao": "Comércio varejista de livros"}, {"codigo": 4781400, "descricao": "Comércio varejista de artigos do vestuário e acessórios"}, {"codigo": 5811500, "descricao": "Edição de livros"}, {"codigo": 6319400, "descricao": "Portais, provedores de conteúdo e outros serviços de informação na internet"}, {"codigo": 7020400, "descricao": "Atividades de consultoria em gestão empresarial, exceto consultoria técnica específica"}, {"codigo": 7319004, "descricao": "Consultoria em publicidade"}, {"codigo": 7490104, "descricao": "Atividades de intermediação e agenciamento de serviços e negócios em geral, exceto imobiliários"}, {"codigo": 7490105, "descricao": "Agenciamento de profissionais para atividades esportivas, culturais e artísticas"}, {"codigo": 8230001, "descricao": "Serviços de organização de feiras, congressos, exposições e festas"}, {"codigo": 8299705, "descricao": "Serviços de levantamento de fundos sob contrato"}, {"codigo": 8592901, "descricao": "Ensino de dança"}, {"codigo": 8599604, "descricao": "Treinamento em desenvolvimento profissional e gerencial"}, {"codigo": 8599699, "descricao": "Outras atividades de ensino não especificadas anteriormente"}, {"codigo": 9001901, "descricao": "Produção teatral"}, {"codigo": 9001902, "descricao": "Produção musical"}, {"codigo": 9001903, "descricao": "Produção de espetáculos de dança"}, {"codigo": 9001999, "descricao": "Artes cênicas, espetáculos e atividades complementares não especificadas anteriormente"}, {"codigo": 9003500, "descricao": "Gestão de espaços para artes cênicas, espetáculos e outras atividades artísticas"}, {"codigo": 9319101, "descricao": "Produção e promoção de eventos esportivos"}], "natureza_juridica": "Sociedade Empresária Limitada", "situacao_especial": "", "opcao_pelo_simples": true, "situacao_cadastral": 2, "data_opcao_pelo_mei": "2015-09-24", "data_exclusao_do_mei": "2022-06-30", "cnae_fiscal_descricao": "Ensino de arte e cultura não especificado anteriormente", "codigo_municipio_ibge": 4318705, "data_inicio_atividade": "2015-09-24", "data_situacao_especial": null, "data_opcao_pelo_simples": "2015-09-24", "data_situacao_cadastral": "2015-09-24", "nome_cidade_no_exterior": "", "codigo_natureza_juridica": 2062, "data_exclusao_do_simples": null, "motivo_situacao_cadastral": 0, "ente_federativo_responsavel": "", "identificador_matriz_filial": 1, "qualificacao_do_responsavel": 49, "descricao_situacao_cadastral": "ATIVA", "descricao_tipo_de_logradouro": "RUA", "descricao_motivo_situacao_cadastral": "SEM MOTIVO", "descricao_identificador_matriz_filial": "MATRIZ"}