{"uf": "MS", "cep": "79300040", "qsa": null, "cnpj": "24602765000160", "pais": null, "email": null, "porte": "EMPRESA DE PEQUENO PORTE", "bairro": "CENTRO", "numero": "749", "ddd_fax": "", "municipio": "CORUMBA", "logradouro": "TREZE DE JUNHO", "cnae_fiscal": 4712100, "codigo_pais": null, "complemento": "", "codigo_porte": 3, "razao_social": "SIMEIA A. H. M. MUSTAFA", "nome_fantasia": "TENTACAO", "capital_social": 120000, "ddd_telefone_1": "6799876248", "ddd_telefone_2": "", "opcao_pelo_mei": false, "descricao_porte": "", "codigo_municipio": 9063, "cnaes_secundarios": [{"codigo": 4721102, "descricao": "Padaria e confeitaria com predominância de revenda"}, {"codigo": 4721103, "descricao": "Comércio varejista de laticínios e frios"}, {"codigo": 4722901, "descricao": "Comércio varejista de carnes - açougues"}, {"codigo": 4723700, "descricao": "Comércio varejista de bebidas"}, {"codigo": 4724500, "descricao": "Comércio varejista de hortifrutigranjeiros"}, {"codigo": 4742300, "descricao": "Comércio varejista de material elétrico"}, {"codigo": 4743100, "descricao": "Comércio varejista de vidros"}, {"codigo": 4744002, "descricao": "Comércio varejista de madeira e artefatos"}, {"codigo": 4744003, "descricao": "Comércio varejista de materiais hidráulicos"}, {"codigo": 4751201, "descricao": "Comércio varejista especializado de equipamentos e suprimentos de informática"}, {"codigo": 4753900, "descricao": "Comércio varejista especializado de eletrodomésticos e equipamentos de áudio e vídeo"}, {"codigo": 4754701, "descricao": "Comércio varejista de móveis"}, {"codigo": 4754702, "descricao": "Comércio varejista de artigos de colchoaria"}, {"codigo": 4754703, "descricao": "Comércio varejista de artigos de iluminação"}, {"codigo": 4755502, "descricao": "Comercio varejista de artigos de armarinho"}, {"codigo": 4756300, "descricao": "Comércio varejista especializado de instrumentos musicais e acessórios"}, {"codigo": 4759899, "descricao": "Comércio varejista de outros artigos de uso pessoal e doméstico não especificados anteriormente"}, {"codigo": 4761001, "descricao": "Comércio varejista de livros"}, {"codigo": 4761003, "descricao": "Comércio varejista de artigos de papelaria"}, {"codigo": 4763602, "descricao": "Comércio varejista de artigos esportivos"}, {"codigo": 4763603, "descricao": "Comércio varejista de bicicletas e triciclos; peças e acessórios"}, {"codigo": 4772500, "descricao": "Comércio varejista de cosméticos, produtos de perfumaria e de higiene pessoal"}, {"codigo": 4781400, "descricao": "Comércio varejista de artigos do vestuário e acessórios"}, {"codigo": 4789099, "descricao": "Comércio varejista de outros produtos não especificados anteriormente"}], "natureza_juridica": "Empresário (Individual)", "situacao_especial": "", "opcao_pelo_simples": true, "situacao_cadastral": 2, "data_opcao_pelo_mei": null, "data_exclusao_do_mei": null, "cnae_fiscal_descricao": "Comércio varejista de mercadorias em geral, com predominância de produtos alimentícios - minimercados, mercearias e armazéns", "codigo_municipio_ibge": 5003207, "data_inicio_atividade": "1988-06-17", "data_situacao_especial": null, "data_opcao_pelo_simples": "2007-07-01", "data_situacao_cadastral": "2005-11-03", "nome_cidade_no_exterior": "", "codigo_natureza_juridica": 2135, "data_exclusao_do_simples": null, "motivo_situacao_cadastral": 0, "ente_federativo_responsavel": "", "identificador_matriz_filial": 1, "qualificacao_do_responsavel": 50, "descricao_situacao_cadastral": "ATIVA", "descricao_tipo_de_logradouro": "RUA", "descricao_motivo_situacao_cadastral": "SEM MOTIVO", "descricao_identificador_matriz_filial": "MATRIZ"}