{"uf": "SP", "cep": "13403846", "qsa": [{"pais": null, "nome_socio": "MATEUS TEIXEIRA MARCONI", "codigo_pais": null, "faixa_etaria": "Entre 41 a 50 anos", "cnpj_cpf_do_socio": "***577448**", "qualificacao_socio": "Titular Pessoa Física Residente ou Domiciliado no Brasil", "codigo_faixa_etaria": 5, "data_entrada_sociedade": "2017-02-10", "identificador_de_socio": 2, "cpf_representante_legal": "***000000**", "nome_representante_legal": "", "codigo_qualificacao_socio": 65, "qualificacao_representante_legal": "Titular Pessoa Física Residente ou Domiciliado no Brasil", "codigo_qualificacao_representante_legal": 0}], "cnpj": "27081522000111", "pais": null, "email": null, "porte": "EMPRESA DE PEQUENO PORTE", "bairro": "TERRAS DE PIRACICABA", "numero": "120", "ddd_fax": "", "municipio": "PIRACICABA", "logradouro": "PROFESSOR SERGIO BONGANHI", "cnae_fiscal": 4789099, "codigo_pais": null, "complemento": "SALA 105", "codigo_porte": 3, "razao_social": "M T MARCONI EIRELI", "nome_fantasia": "", "capital_social": 100000, "ddd_telefone_1": "1930350666", "ddd_telefone_2": "", "opcao_pelo_mei": false, "descricao_porte": "", "codigo_municipio": 6875, "cnaes_secundarios": [{"codigo": 3312102, "descricao": "Manutenção e reparação de aparelhos e instrumentos de medida, teste e controle"}, {"codigo": 7739099, "descricao": "Aluguel de outras máquinas e equipamentos comerciais e industriais não especificados anteriormente, sem operador"}, {"codigo": 3319800, "descricao": "Manutenção e reparação de equipamentos e produtos não especificados anteriormente"}], "natureza_juridica": "Empresa Individual de Responsabilidade Limitada (de Natureza Empresária)", "situacao_especial": "", "opcao_pelo_simples": false, "situacao_cadastral": 2, "data_opcao_pelo_mei": null, "data_exclusao_do_mei": null, "cnae_fiscal_descricao": "Comércio varejista de outros produtos não especificados anteriormente", "codigo_municipio_ibge": 3538709, "data_inicio_atividade": "2017-02-10", "data_situacao_especial": null, "data_opcao_pelo_simples": "2019-01-01", "data_situacao_cadastral": "2017-02-10", "nome_cidade_no_exterior": "", "codigo_natureza_juridica": 2305, "data_exclusao_do_simples": "2021-12-31", "motivo_situacao_cadastral": 0, "ente_federativo_responsavel": "", "identificador_matriz_filial": 1, "qualificacao_do_responsavel": 65, "descricao_situacao_cadastral": "ATIVA", "descricao_tipo_de_logradouro": "PRACA", "descricao_motivo_situacao_cadastral": "SEM MOTIVO", "descricao_identificador_matriz_filial": "MATRIZ"}