{"uf": "TO", "cep": "77006388", "qsa": null, "cnpj": "31598672000174", "pais": null, "email": null, "porte": "MICRO EMPRESA", "bairro": "PLANO DIRETOR NORTE", "numero": "9", "ddd_fax": "", "municipio": "PALMAS", "logradouro": "ACSU NE 50 RUA 2 B", "cnae_fiscal": 8592999, "codigo_pais": null, "complemento": "COND PALMEIRA IMPERIAL 12 207", "codigo_porte": 1, "razao_social": "ELTON DOUGLAS FIALHO BARATA 93731272253", "nome_fantasia": "EDFB PRODUCAO CULTURAL", "capital_social": 10000, "ddd_telefone_1": "6332174675", "ddd_telefone_2": "", "opcao_pelo_mei": false, "descricao_porte": "", "codigo_municipio": 9733, "cnaes_secundarios": [{"codigo": 8599699, "descricao": "Outras atividades de ensino não especificadas anteriormente"}, {"codigo": 5912099, "descricao": "Atividades de pós-produção cinematográfica, de vídeos e de programas de televisão não especificadas anteriormente"}, {"codigo": 9001901, "descricao": "Produção teatral"}, {"codigo": 5229099, "descricao": "Outras atividades auxiliares dos transportes terrestres não especificadas anteriormente"}, {"codigo": 8592902, "descricao": "Ensino de artes cênicas, exceto dança"}, {"codigo": 8230001, "descricao": "Serviços de organização de feiras, congressos, exposições e festas"}, {"codigo": 7420001, "descricao": "Atividades de produção de fotografias, exceto aérea e submarina"}], "natureza_juridica": "Empresário (Individual)", "situacao_especial": "", "opcao_pelo_simples": false, "situacao_cadastral": 8, "data_opcao_pelo_mei": "2018-09-25", "data_exclusao_do_mei": "2021-10-20", "cnae_fiscal_descricao": "Ensino de arte e cultura não especificado anteriormente", "codigo_municipio_ibge": 1721000, "data_inicio_atividade": "2018-09-25", "data_situacao_especial": null, "data_opcao_pelo_simples": "2018-09-25", "data_situacao_cadastral": "2021-10-20", "nome_cidade_no_exterior": "", "codigo_natureza_juridica": 2135, "data_exclusao_do_simples": "2021-10-20", "motivo_situacao_cadastral": 1, "ente_federativo_responsavel": "", "identificador_matriz_filial": 1, "qualificacao_do_responsavel": 50, "descricao_situacao_cadastral": "BAIXADA", "descricao_tipo_de_logradouro": "QUADRA", "descricao_motivo_situacao_cadastral": "EXTINCAO POR ENCERRAMENTO LIQUIDACAO VOLUNTARIA", "descricao_identificador_matriz_filial": "MATRIZ"}