{"uf": "SP", "cep": "03648000", "qsa": [{"pais": null, "nome_socio": "LUCIANA DE FATIMA ZANETTI", "codigo_pais": null, "faixa_etaria": "Entre 41 a 50 anos", "cnpj_cpf_do_socio": "***418668**", "qualificacao_socio": "Titular Pessoa Física Residente ou Domiciliado no Brasil", "codigo_faixa_etaria": 5, "data_entrada_sociedade": "2019-02-04", "identificador_de_socio": 2, "cpf_representante_legal": "***000000**", "nome_representante_legal": "", "codigo_qualificacao_socio": 65, "qualificacao_representante_legal": "Titular Pessoa Física Residente ou Domiciliado no Brasil", "codigo_qualificacao_representante_legal": 0}], "cnpj": "32648650000134", "pais": null, "email": null, "porte": "EMPRESA DE PEQUENO PORTE", "bairro": "VILA ESPERANCA", "numero": "392", "ddd_fax": "", "municipio": "SAO PAULO", "logradouro": "PDES OLIVETANOS", "cnae_fiscal": 4751201, "codigo_pais": null, "complemento": "", "codigo_porte": 3, "razao_social": "SDK COMERCIO DE SUPRIMENTOS PARA INFORMATICA EIRELI", "nome_fantasia": "SDK INFORMATICA", "capital_social": 99800, "ddd_telefone_1": "1129390286", "ddd_telefone_2": "", "opcao_pelo_mei": false, "descricao_porte": "", "codigo_municipio": 7107, "cnaes_secundarios": [{"codigo": 4742300, "descricao": "Comércio varejista de material elétrico"}, {"codigo": 4744001, "descricao": "Comércio varejista de ferragens e ferramentas"}, {"codigo": 4744099, "descricao": "Comércio varejista de materiais de construção em geral"}, {"codigo": 4754703, "descricao": "Comércio varejista de artigos de iluminação"}, {"codigo": 4761003, "descricao": "Comércio varejista de artigos de papelaria"}, {"codigo": 4789005, "descricao": "Comércio varejista de produtos saneantes domissanitários"}], "natureza_juridica": "Empresa Individual de Responsabilidade Limitada (de Natureza Empresária)", "situacao_especial": "", "opcao_pelo_simples": true, "situacao_cadastral": 2, "data_opcao_pelo_mei": null, "data_exclusao_do_mei": null, "cnae_fiscal_descricao": "Comércio varejista especializado de equipamentos e suprimentos de informática", "codigo_municipio_ibge": 3550308, "data_inicio_atividade": "2019-02-04", "data_situacao_especial": null, "data_opcao_pelo_simples": "2019-02-04", "data_situacao_cadastral": "2019-02-04", "nome_cidade_no_exterior": "", "codigo_natureza_juridica": 2305, "data_exclusao_do_simples": null, "motivo_situacao_cadastral": 0, "ente_federativo_responsavel": "", "identificador_matriz_filial": 1, "qualificacao_do_responsavel": 65, "descricao_situacao_cadastral": "ATIVA", "descricao_tipo_de_logradouro": "AVENIDA", "descricao_motivo_situacao_cadastral": "SEM MOTIVO", "descricao_identificador_matriz_filial": "MATRIZ"}