{"uf": "SP", "cep": "14470000", "qsa": [{"pais": null, "nome_socio": "SILVANE CRISTINA DOS SANTOS VICENTE", "codigo_pais": null, "faixa_etaria": "Entre 31 a 40 anos", "cnpj_cpf_do_socio": "***436806**", "qualificacao_socio": "Sócio-Administrador", "codigo_faixa_etaria": 4, "data_entrada_sociedade": "2022-03-02", "identificador_de_socio": 2, "cpf_representante_legal": "***000000**", "nome_representante_legal": "", "codigo_qualificacao_socio": 49, "qualificacao_representante_legal": "Sócio-Administrador", "codigo_qualificacao_representante_legal": 0}], "cnpj": "35316374000103", "pais": null, "email": null, "porte": "MICRO EMPRESA", "bairro": "CENTRO", "numero": "11", "ddd_fax": "", "municipio": "PEDREGULHO", "logradouro": "JOAQUIM FERREIRA COELHO", "cnae_fiscal": 6190601, "codigo_pais": null, "complemento": "", "codigo_porte": 1, "razao_social": "POWER TECNOLOGIA E TELECOMUNICACOES LTDA", "nome_fantasia": "POWER TECNOLOGIA E TELECOMUNICACOES", "capital_social": 400000, "ddd_telefone_1": "1697613881", "ddd_telefone_2": "", "opcao_pelo_mei": false, "descricao_porte": "", "codigo_municipio": 6841, "cnaes_secundarios": [{"codigo": 4751201, "descricao": "Comércio varejista especializado de equipamentos e suprimentos de informática"}, {"codigo": 4752100, "descricao": "Comércio varejista especializado de equipamentos de telefonia e comunicação"}, {"codigo": 4753900, "descricao": "Comércio varejista especializado de eletrodomésticos e equipamentos de áudio e vídeo"}, {"codigo": 4754701, "descricao": "Comércio varejista de móveis"}, {"codigo": 4761003, "descricao": "Comércio varejista de artigos de papelaria"}, {"codigo": 4789007, "descricao": "Comércio varejista de equipamentos para escritório"}, {"codigo": 4789008, "descricao": "Comércio varejista de artigos fotográficos e para filmagem"}, {"codigo": 6202300, "descricao": "Desenvolvimento e licenciamento de programas de computador customizáveis"}, {"codigo": 6203100, "descricao": "Desenvolvimento e licenciamento de programas de computador não-customizáveis"}, {"codigo": 7490104, "descricao": "Atividades de intermediação e agenciamento de serviços e negócios em geral, exceto imobiliários"}, {"codigo": 7733100, "descricao": "Aluguel de máquinas e equipamentos para escritórios"}, {"codigo": 9511800, "descricao": "Reparação e manutenção de computadores e de equipamentos periféricos"}], "natureza_juridica": "Sociedade Empresária Limitada", "situacao_especial": "", "opcao_pelo_simples": false, "situacao_cadastral": 2, "data_opcao_pelo_mei": null, "data_exclusao_do_mei": null, "cnae_fiscal_descricao": "Provedores de acesso às redes de comunicações", "codigo_municipio_ibge": 3537008, "data_inicio_atividade": "2019-10-25", "data_situacao_especial": null, "data_opcao_pelo_simples": "2019-10-25", "data_situacao_cadastral": "2019-10-25", "nome_cidade_no_exterior": "", "codigo_natureza_juridica": 2062, "data_exclusao_do_simples": "2021-10-31", "motivo_situacao_cadastral": 0, "ente_federativo_responsavel": "", "identificador_matriz_filial": 1, "qualificacao_do_responsavel": 49, "descricao_situacao_cadastral": "ATIVA", "descricao_tipo_de_logradouro": "RUA", "descricao_motivo_situacao_cadastral": "SEM MOTIVO", "descricao_identificador_matriz_filial": "MATRIZ"}