{"uf": "RO", "cep": "76929000", "qsa": null, "cnpj": "63787097000144", "pais": null, "email": null, "porte": "DEMAIS", "bairro": " ALTO ALEGRE", "numero": "4872", "ddd_fax": "", "municipio": "URUPA", "logradouro": "GOVERNADOR JORGE TEIXEIRA", "cnae_fiscal": 8411600, "codigo_pais": null, "complemento": "SETOR 04 Q.10 LT 07", "codigo_porte": 5, "razao_social": "MUNICIPIO DE URUPA", "nome_fantasia": "PREFEITURA MUNICIPAL DE URUPA", "capital_social": 0, "ddd_telefone_1": "0694132545", "ddd_telefone_2": "", "opcao_pelo_mei": null, "descricao_porte": "", "codigo_municipio": 977, "cnaes_secundarios": [{"codigo": 0, "descricao": ""}], "natureza_juridica": "Município", "situacao_especial": "", "opcao_pelo_simples": null, "situacao_cadastral": 2, "data_opcao_pelo_mei": null, "data_exclusao_do_mei": null, "cnae_fiscal_descricao": "Administração pública em geral", "codigo_municipio_ibge": 1101708, "data_inicio_atividade": "1994-08-02", "data_situacao_especial": null, "data_opcao_pelo_simples": null, "data_situacao_cadastral": "2005-01-15", "nome_cidade_no_exterior": "", "codigo_natureza_juridica": 1244, "data_exclusao_do_simples": null, "motivo_situacao_cadastral": 0, "ente_federativo_responsavel": "URUPA - RO", "identificador_matriz_filial": 1, "qualificacao_do_responsavel": 5, "descricao_situacao_cadastral": "ATIVA", "descricao_tipo_de_logradouro": "AVENIDA", "descricao_motivo_situacao_cadastral": "SEM MOTIVO", "descricao_identificador_matriz_filial": "MATRIZ"}