{"uf": "AM", "cep": "69041240", "qsa": null, "cnpj": "84497130000171", "pais": null, "email": null, "porte": "MICRO EMPRESA", "bairro": "TARUMA", "numero": "25", "ddd_fax": "", "municipio": "MANAUS", "logradouro": "FLOR DO CAMPO", "cnae_fiscal": 8211300, "codigo_pais": null, "complemento": "", "codigo_porte": 1, "razao_social": "E J N DE ARAUJO", "nome_fantasia": "COMERCIO E REPRESENTACAO TRANSAMAZONIA", "capital_social": 300000, "ddd_telefone_1": "9292122231", "ddd_telefone_2": "", "opcao_pelo_mei": false, "descricao_porte": "", "codigo_municipio": 255, "cnaes_secundarios": [{"codigo": 2512800, "descricao": "Fabricação de esquadrias de metal"}, {"codigo": 2542000, "descricao": "Fabricação de artigos de serralheria, exceto esquadrias"}, {"codigo": 3314707, "descricao": "Manutenção e reparação de máquinas e aparelhos de refrigeração e ventilação para uso industrial e comercial"}, {"codigo": 3811400, "descricao": "Coleta de resíduos não-perigosos"}, {"codigo": 3832700, "descricao": "Recuperação de materiais plásticos"}, {"codigo": 4213800, "descricao": "Obras de urbanização - ruas, praças e calçadas"}, {"codigo": 4321500, "descricao": "Instalação e manutenção elétrica"}, {"codigo": 4399103, "descricao": "Obras de alvenaria"}, {"codigo": 4399199, "descricao": "Serviços especializados para construção não especificados anteriormente"}, {"codigo": 4530703, "descricao": "Comércio a varejo de peças e acessórios novos para veículos automotores"}, {"codigo": 4639701, "descricao": "Comércio atacadista de produtos alimentícios em geral"}, {"codigo": 4712100, "descricao": "Comércio varejista de mercadorias em geral, com predominância de produtos alimentícios - minimercados, mercearias e armazéns"}, {"codigo": 4741500, "descricao": "Comércio varejista de tintas e materiais para pintura"}, {"codigo": 4744002, "descricao": "Comércio varejista de madeira e artefatos"}, {"codigo": 4744099, "descricao": "Comércio varejista de materiais de construção em geral"}, {"codigo": 5212500, "descricao": "Carga e descarga"}, {"codigo": 5620101, "descricao": "Fornecimento de alimentos preparados preponderantemente para empresas"}, {"codigo": 8011101, "descricao": "Atividades de vigilância e segurança privada"}, {"codigo": 8020001, "descricao": "Atividades de monitoramento de sistemas de segurança eletrônico"}, {"codigo": 8111700, "descricao": "Serviços combinados para apoio a edifícios, exceto condomínios prediais"}, {"codigo": 8121400, "descricao": "Limpeza em prédios e em domicílios"}, {"codigo": 8130300, "descricao": "Atividades paisagísticas"}], "natureza_juridica": "Empresário (Individual)", "situacao_especial": "", "opcao_pelo_simples": true, "situacao_cadastral": 2, "data_opcao_pelo_mei": null, "data_exclusao_do_mei": null, "cnae_fiscal_descricao": "Serviços combinados de escritório e apoio administrativo", "codigo_municipio_ibge": 1302603, "data_inicio_atividade": "1993-11-01", "data_situacao_especial": null, "data_opcao_pelo_simples": "2019-01-01", "data_situacao_cadastral": "2004-10-30", "nome_cidade_no_exterior": "", "codigo_natureza_juridica": 2135, "data_exclusao_do_simples": null, "motivo_situacao_cadastral": 0, "ente_federativo_responsavel": "", "identificador_matriz_filial": 1, "qualificacao_do_responsavel": 50, "descricao_situacao_cadastral": "ATIVA", "descricao_tipo_de_logradouro": "RUA", "descricao_motivo_situacao_cadastral": "SEM MOTIVO", "descricao_identificador_matriz_filial": "MATRIZ"}