{"id":139,"ano":"2020","autor":"RELATOR GERAL","numeroEmenda":"0275","localidade":"Sudeste","funcao":"Saneamento","subfuncao":"Saneamento básico urbano","empenhado":"25.876.789,00","liquido":"25.876.639,00","pago":"25.876.639,00","codigoEmenda":"202081000275","valorRestoInscrito":"150,00","valorRestoCancelado":"0,00","valorRestoPago":"0,00","valorRestoAPagar":null,"quantidadeDocumentos":95,"documentos":[{"id":23353278,"data":"24/04/2020","fase":"Liquidação","codigoDocumento":"175004000012020NS008225","codigoDocumentoResumido":"2020NS008225","especieTipo":"","observacao":"OF CIDADES 011 DE 22/04/2020 CR.NR.0424403-36","tipo":"","valorDocumento":"","descricao":"Nota de Lançamento de Sistema (NS)","favorecido":{"id":27462634,"docFavorecido":"17.749.896/0001-09","nome":"MUNICIPIO DE SAO JOAO DEL REI","tipo":"Pessoa Jurídica","url":"https://www.portaltransparencia.gov.br/pessoa-juridica/17749896000109"},"orgaoPagador":{"id":195069,"orgaoSuperiorCod":"53000","orgaoSuperiorNome":"Ministério do Desenvolvimento Regional","entidadeVinculadaCod":"53000","entidadeVinculadaNome":"Ministério do Desenvolvimento Regional - Unidades com vínculo direto","unidadeGestoraCod":"175004","unidadeGestoraNome":"CAIXA ECONOMICA FEDERAL - PROGRAMAS SOCIAIS","gestaoCod":"00001","gestaoNome":"TESOURO NACIONAL","url":"https://www.portaltransparencia.gov.br/orgaos/53000-ministerio-do-desenvolvimento-regional"}},{"id":23353370,"data":"26/06/2020","fase":"Liquidação","codigoDocumento":"175004000012020NS017165","codigoDocumentoResumido":"2020NS017165","especieTipo":"","observacao":"OF CIDADES 040 DE 18/06/2020 CR.NR.0408644-13","tipo":"","valorDocumento":"","descricao":"Nota de Lançamento de Sistema (NS)","favorecido":{"id":5923932,"docFavorecido":"46.588.950/0001-80","nome":"MUNICIPIO DE SAO JOSE DO RIO PRETO","tipo":"Pessoa Jurídica","url":"https://www.portaltransparencia.gov.br/pessoa-juridica/46588950000180"},"orgaoPagador":{"id":195069,"orgaoSuperiorCod":"53000","orgaoSuperiorNome":"Ministério do Desenvolvimento Regional","entidadeVinculadaCod":"53000","entidadeVinculadaNome":"Ministério do Desenvolvimento Regional - Unidades com vínculo direto","unidadeGestoraCod":"175004","unidadeGestoraNome":"CAIXA ECONOMICA FEDERAL - PROGRAMAS SOCIAIS","gestaoCod":"00001","gestaoNome":"TESOURO NACIONAL","url":"https://www.portaltransparencia.gov.br/orgaos/53000-ministerio-do-desenvolvimento-regional"}},{"id":23353398,"data":"13/08/2020","fase":"Liquidação","codigoDocumento":"175004000012020NS024215","codigoDocumentoResumido":"2020NS024215","especieTipo":"","observacao":"OF CIDADES 070 DE 10/08/2020 CR.NR.0426312-86","tipo":"","valorDocumento":"","descricao":"Nota de Lançamento de Sistema (NS)","favorecido":{"id":2056700,"docFavorecido":"44.892.693/0001-40","nome":"MUNICIPIO DE CARAPICUIBA","tipo":"Pessoa Jurídica","url":"https://www.portaltransparencia.gov.br/pessoa-juridica/44892693000140"},"orgaoPagador":{"id":195069,"orgaoSuperiorCod":"53000","orgaoSuperiorNome":"Ministério do Desenvolvimento Regional","entidadeVinculadaCod":"53000","entidadeVinculadaNome":"Ministério do Desenvolvimento Regional - Unidades com vínculo direto","unidadeGestoraCod":"175004","unidadeGestoraNome":"CAIXA ECONOMICA FEDERAL - PROGRAMAS SOCIAIS","gestaoCod":"00001","gestaoNome":"TESOURO NACIONAL","url":"https://www.portaltransparencia.gov.br/orgaos/53000-ministerio-do-desenvolvimento-regional"}},{"id":1166046,"data":"31/12/2020","fase":"Liquidação","codigoDocumento":"175004000012020NS041689","codigoDocumentoResumido":"2020NS041689","especieTipo":"","observacao":"INSCRICAO DE EMPENHOS EM RESTOS A PAGAR NAO PROCESSADOS A LIQUIDAR E EM LIQUI-DACAO CONFORME INDICACAO DO ORDENADOR DE DESPESA, COM BASE NOS SALDOS DAS CON-TAS 89991.33.01 E 89991.33.03.","tipo":"","valorDocumento":"","descricao":"Nota de Lançamento de Sistema (NS)","favorecido":{"id":579002,"docFavorecido":"-1","nome":"Sem informação","tipo":"Não Listado","url":""},"orgaoPagador":{"id":195069,"orgaoSuperiorCod":"53000","orgaoSuperiorNome":"Ministério do Desenvolvimento Regional","entidadeVinculadaCod":"53000","entidadeVinculadaNome":"Ministério do Desenvolvimento Regional - Unidades com vínculo direto","unidadeGestoraCod":"175004","unidadeGestoraNome":"CAIXA ECONOMICA FEDERAL - PROGRAMAS SOCIAIS","gestaoCod":"00001","gestaoNome":"TESOURO NACIONAL","url":"https://www.portaltransparencia.gov.br/orgaos/53000-ministerio-do-desenvolvimento-regional"}},{"id":23353427,"data":"16/12/2021","fase":"Liquidação","codigoDocumento":"175004000012021NS028629","codigoDocumentoResumido":"2021NS028629","especieTipo":"","observacao":"CE GEOTR 1113/21 EM ATENDIMENTO AO COMUNICADO Nº 033/2020 DO ME - OFICIO Nº 99/2021/SNS (MDR)-MDR CONTRATO: 042442827 LIQUIDACAO PARCELA CONTRATO","tipo":"","valorDocumento":"","descricao":"Nota de Lançamento de Sistema (NS)","favorecido":{"id":2501417,"docFavorecido":"27.165.729/0001-74","nome":"MUNICIPIO DE COLATINA","tipo":"Pessoa Jurídica","url":"https://www.portaltransparencia.gov.br/pessoa-juridica/27165729000174"},"orgaoPagador":{"id":195069,"orgaoSuperiorCod":"53000","orgaoSuperiorNome":"Ministério do Desenvolvimento Regional","entidadeVinculadaCod":"53000","entidadeVinculadaNome":"Ministério do Desenvolvimento Regional - Unidades com vínculo direto","unidadeGestoraCod":"175004","unidadeGestoraNome":"CAIXA ECONOMICA FEDERAL - PROGRAMAS SOCIAIS","gestaoCod":"00001","gestaoNome":"TESOURO NACIONAL","url":"https://www.portaltransparencia.gov.br/orgaos/53000-ministerio-do-desenvolvimento-regional"}}]}